RelativeToNow/__init__.py
relative_to_now-1.1.0.dist-info/WHEEL
relative_to_now-1.1.0.dist-info/LICENSE
relative_to_now-1.1.0.dist-info/METADATA
relative_to_now-1.1.0.dist-info/RECORD
