Metadata-Version: 2.1
Name: relative-to-now
Version: 1.1.0
Summary: Print a datetime's distance from now
Home-page: https://github.com/Riverside-Healthcare/RelativeToNow
License: GPL-3.0-or-later
Author: Christopher Pickering
Author-email: cpickering@rhc.net
Maintainer: Christopher Pickering
Maintainer-email: cpickering@rhc.net
Requires-Python: >=3.7.2,<4.0.0
Classifier: Development Status :: 5 - Production/Stable
Classifier: License :: OSI Approved :: GNU General Public License v3 or later (GPLv3+)
Classifier: Operating System :: OS Independent
Classifier: Programming Language :: Python :: 3
Classifier: Programming Language :: Python :: 3.8
Classifier: Programming Language :: Python :: 3.9
Classifier: Programming Language :: Python :: 3.10
Classifier: Programming Language :: Python :: 3.11
Classifier: Programming Language :: Python :: 3
Project-URL: Documentation, https://github.com/Riverside-Healthcare/RelativeToNow
Project-URL: Repository, https://github.com/Riverside-Healthcare/RelativeToNow
